dataclass_settings/__init__.py
dataclass_settings/base.py
dataclass_settings/class_inspect.py
dataclass_settings/context.py
dataclass_settings/loader.py
dataclass_settings/py.typed
dataclass_settings/loaders/__init__.py
dataclass_settings/loaders/env.py
dataclass_settings/loaders/secret.py
dataclass_settings/loaders/toml.py
dataclass_settings-0.7.0.dist-info/METADATA
dataclass_settings-0.7.0.dist-info/WHEEL
dataclass_settings-0.7.0.dist-info/licenses/LICENSE
dataclass_settings-0.7.0.dist-info/RECORD
