Metadata-Version: 2.4
Name: dataclass-settings
Version: 0.7.0
Summary: Declarative dataclass settings.
Project-URL: repository, https://github.com/dancardin/dataclass-settings
Author-email: Dan Cardin <ddcardin@gmail.com>
License:                                  Apache License
License-File: LICENSE
Keywords: attrs,dataclass,env,msgspec,pydantic,settings
Classifier: Topic :: Software Development :: Libraries :: Python Modules
Requires-Python: <4,>=3.8
Requires-Dist: type-lens>=0.2.5
Requires-Dist: typing-extensions>=4.7.1
